setup.py
bin/modelpai
modelpai/__init__.py
modelpai/osscmd.py
modelpai.egg-info/PKG-INFO
modelpai.egg-info/SOURCES.txt
modelpai.egg-info/dependency_links.txt
modelpai.egg-info/requires.txt
modelpai.egg-info/top_level.txt
modelpai/oss/__init__.py
modelpai/oss/oss_api.py
modelpai/oss/oss_sample.py
modelpai/oss/oss_util.py
modelpai/oss/oss_xml_handler.py
modelpai/oss/pkg_info.py