Metadata-Version: 1.0
Name: modelpai
Version: 0.0.34
Summary: upload models to pai for training and republishing
Home-page: UNKNOWN
Author: acelin
Author-email: chaohui.lch@alibaba-inc.com
License: MIT Licence
Keywords: pai
Platform: any
